<?xml version="1.0" encoding="UTF-8"?><SI_RESOURCES xmlns="http://www.stercomm.com/SI/SI_IE_Resources" xmlns:xsi="http://www.w3.org/2001/XMLSchema-instance" GISVersion="6000" passphraseCheckString="rO0ABXQABkRFU2VkZXVyAAJbQqzzF/gGCFTgAgAAeHAAAAAIVqGkCL5Tj7JzcgARamF2YS5sYW5nLkludGVnZXIS4qCk94GHOAIAAUkABXZhbHVleHIAEGphdmEubGFuZy5OdW1iZXKGrJUdC5TgiwIAAHhwAAAAZXVxAH4AAQAAABDRJ+sG8QGqQmtiXJKzcvqD" FrameworkVersion="2"><SERVICE_INSTANCES><SERVICE_INSTANCE><parentdefname>FileSystem</parentdefname><name>BBVAsrvLTfsDEFAULT</name><groupname></groupname><displayname>BBVAsrvLTfsDEFAULT</displayname><description>BBVAsrvLTfsDEFAULT</description><targetenv>node1</targetenv><activestatus>1</activestatus><systemservice>0</systemservice><parentdefid>-1</parentdefid><PARM><name>assignFilename</name><value>false</value></PARM><PARM><name>bootstrap</name><value>false</value></PARM><PARM><name>collectionFolder</name><value>/gmm</value></PARM><PARM><name>extractionFolder</name><value>/gmm</value></PARM><PARM><name>keepPath</name><value>false</value></PARM><PARM><name>unobscure</name><value>false</value></PARM><PARM><name>useSubFolders</name><value>false</value></PARM></SERVICE_INSTANCE><SERVICE_INSTANCE><parentdefname>LightweightJDBCAdapterType</parentdefname><name>BBVAsrvLTlwjdbcORACLE</name><groupname></groupname><displayname>BBVAsrvLTlwjdbcORACLE</displayname><description>BBVAsrvLTlwjdbcORACLE</description><targetenv>node1</targetenv><activestatus>1</activestatus><systemservice>0</systemservice><parentdefid>-1</parentdefid><PARM><name>StartNewWorkFlow</name><value>NO</value></PARM><PARM><name>pool</name><value>BBVApoolOracle</value></PARM></SERVICE_INSTANCE></SERVICE_INSTANCES></SI_RESOURCES>